python_gettext_translations/__init__.py
python_gettext_translations/storage.py
python_gettext_translations/translations.py
python_gettext_translations-1.1.0.dist-info/WHEEL
python_gettext_translations-1.1.0.dist-info/METADATA
python_gettext_translations-1.1.0.dist-info/RECORD
