Metadata-Version: 2.1
Name: python-gettext-translations
Version: 1.1.0
Summary: Python gettext translations
Keywords: translations,i18n,i18n_mrg
Author-email: Alexey Zauzin <a.zauzin@thestage.ai>
Requires-Python: >=3.7
Requires-Dist: importlib-metadata; python_version<"3.8"
Requires-Dist: polib
